okxpy_guagua/__init__.py
okxpy_guagua/okx_guagua.py
okxpy_guagua-0.1.4.dist-info/licenses/LICENSE
okxpy_guagua-0.1.4.dist-info/METADATA
okxpy_guagua-0.1.4.dist-info/WHEEL
okxpy_guagua-0.1.4.dist-info/top_level.txt
okxpy_guagua-0.1.4.dist-info/RECORD
