Metadata-Version: 2.4
Name: okxpy_guagua
Version: 0.1.4
Summary: 使用python的网络请求库requests实现okx加密货币交易所的api交互
Author-email: guagua <guagua1053@gmail.com>
Maintainer-email: "jex.huang" <guagua1053@gmail.com>
License: MIT License
Project-URL: Homepage, https://github.com/dream-until-dawn/OKX-PYTHON-GUAGUA
Project-URL: Bug Reports, https://github.com/dream-until-dawn/OKX-PYTHON-GUAGUA/issues
Keywords: jex,okx,python
Classifier: Programming Language :: Python :: 3
Classifier: Operating System :: OS Independent
Requires-Python: >=3.9
License-File: LICENSE
Requires-Dist: requests
Provides-Extra: dev
Requires-Dist: check-manifest; extra == "dev"
Provides-Extra: test
Requires-Dist: coverage; extra == "test"
Dynamic: license-file
